{
  "generator-jhipster": {
    "applicationType": "monolith",
    "gitCompany": "",
    "baseName": "ecom",
    "packageName": "com.mycompany.myapp",
    "packageFolder": "com/mycompany/myapp",
    "serverPort": 8080,
    "serviceDiscoveryType": false,
    "authenticationType": "jwt",
    "uaaBaseName": "../uaa",
    "cacheProvider": "ehcache",
    "enableHibernateCache": true,
    "websocket": false,
    "databaseType": "sql",
    "devDatabaseType": "mysql",
    "prodDatabaseType": "mysql",
    "searchEngine": false,
    "enableSwaggerCodegen": false,
    "messageBroker": false,
    "buildTool": "maven",
    "useSass": true,
    "clientPackageManager": "npm",
    "testFrameworks": ["protractor"],
    "enableTranslation": true,
    "nativeLanguage": "fr",
    "languages": ["en", "fr"],
    "clientFramework": "angularX",
    "jhiPrefix": "jhi",
    "jhipsterVersion": "6.10.5",
    "jwtSecretKey": "YTQyZjZjM2UyYzg5MDU5ZGVhZWU0OTVlMDk2NDQ0ZDViMzg0YjQwMzg4MDIyNmVhMTk4MGM0NmMyM2ZlMTMwZWVhMmZlN2FkNjQ1NzA3N2E5ZDliNDJjYzhhZjRiMDAwYjcxN2E2Y2E0M2VkNzMxNGE1NzQwYTliMjk0NWIwNjI=",
    "embeddableLaunchScript": false,
    "clientTheme": "none",
    "creationTimestamp": 1610552261962,
    "entitySuffix": "",
    "dtoSuffix": "DTO",
    "otherModules": [],
    "blueprints": [],
    "prettierJava": true
  },
  "git-provider": "GitHub",
  "git-company": "asseck",
  "repository-name": "ecom"
}
